{"v":5,"entries":{"configure-your-project--docs":{"id":"configure-your-project--docs","title":"Configure your project","name":"Docs","importPath":"./src/stories/configure.mdx","storiesImports":[],"type":"docs","tags":["dev","test","unattached-mdx"]},"cf-banner--docs":{"id":"cf-banner--docs","title":"CF/Banner","name":"Docs","importPath":"./src/stories/cf/cf-banner.stories.tsx","type":"docs","tags":["dev","test","autodocs"],"storiesImports":[]},"cf-banner--banner":{"type":"story","id":"cf-banner--banner","name":"Banner","title":"CF/Banner","importPath":"./src/stories/cf/cf-banner.stories.tsx","componentPath":"./src/libs/cf/index.ts","tags":["dev","test","autodocs"]},"cf-header--docs":{"id":"cf-header--docs","title":"CF/Header","name":"Docs","importPath":"./src/stories/cf/cf-header.stories.tsx","type":"docs","tags":["dev","test","autodocs"],"storiesImports":[]},"cf-header--header":{"type":"story","id":"cf-header--header","name":"Header","title":"CF/Header","importPath":"./src/stories/cf/cf-header.stories.tsx","componentPath":"./src/libs/cf/index.ts","tags":["dev","test","autodocs"]},"cf-image--docs":{"id":"cf-image--docs","title":"CF/Image","name":"Docs","importPath":"./src/stories/cf/cf-image.stories.tsx","type":"docs","tags":["dev","test","autodocs"],"storiesImports":[]},"cf-image--image":{"type":"story","id":"cf-image--image","name":"Image","title":"CF/Image","importPath":"./src/stories/cf/cf-image.stories.tsx","componentPath":"./src/libs/cf/index.ts","tags":["dev","test","autodocs"]},"cf-lockup--docs":{"id":"cf-lockup--docs","title":"CF/Lockup","name":"Docs","importPath":"./src/stories/cf/cf-lockup.stories.tsx","type":"docs","tags":["dev","test","autodocs"],"storiesImports":[]},"cf-lockup--lockup-image":{"type":"story","id":"cf-lockup--lockup-image","name":"Lockup Image","title":"CF/Lockup","importPath":"./src/stories/cf/cf-lockup.stories.tsx","componentPath":"./src/libs/cf/index.ts","tags":["dev","test","autodocs"]},"cf-lockup--lockup-video":{"type":"story","id":"cf-lockup--lockup-video","name":"Lockup Video","title":"CF/Lockup","importPath":"./src/stories/cf/cf-lockup.stories.tsx","componentPath":"./src/libs/cf/index.ts","tags":["dev","test","autodocs"]},"cf-video-embed--docs":{"id":"cf-video-embed--docs","title":"CF/Video Embed","name":"Docs","importPath":"./src/stories/cf/cf-video-embed.stories.tsx","type":"docs","tags":["dev","test","autodocs"],"storiesImports":[]},"cf-video-embed--video-embed":{"type":"story","id":"cf-video-embed--video-embed","name":"Video Embed","title":"CF/Video Embed","importPath":"./src/stories/cf/cf-video-embed.stories.tsx","componentPath":"./src/libs/cf/index.ts","tags":["dev","test","autodocs"]},"pages-page--logged-out":{"type":"story","id":"pages-page--logged-out","name":"Logged Out","title":"Pages/Page","importPath":"./src/stories/page.stories.ts","componentPath":"./src/stories/page.tsx","tags":["dev","test"]},"pages-page--logged-in":{"type":"story","id":"pages-page--logged-in","name":"Logged In","title":"Pages/Page","importPath":"./src/stories/page.stories.ts","componentPath":"./src/stories/page.tsx","tags":["dev","test","play-fn"]},"ui-accordions--docs":{"id":"ui-accordions--docs","title":"UI/Accordions","name":"Docs","importPath":"./src/stories/ui/accordions.stories.tsx","type":"docs","tags":["dev","test","autodocs"],"storiesImports":[]},"ui-accordions--default":{"type":"story","id":"ui-accordions--default","name":"Default","title":"UI/Accordions","importPath":"./src/stories/ui/accordions.stories.tsx","componentPath":"./src/libs/ui/index.ts","tags":["dev","test","autodocs"]},"ui-animations--docs":{"id":"ui-animations--docs","title":"UI/Animations","name":"Docs","importPath":"./src/stories/ui/animations.stories.tsx","type":"docs","tags":["dev","test","autodocs"],"storiesImports":[]},"ui-animations--collapse":{"type":"story","id":"ui-animations--collapse","name":"Collapse","title":"UI/Animations","importPath":"./src/stories/ui/animations.stories.tsx","componentPath":"./src/libs/ui/index.ts","tags":["dev","test","autodocs"]},"ui-animations--fade":{"type":"story","id":"ui-animations--fade","name":"Fade","title":"UI/Animations","importPath":"./src/stories/ui/animations.stories.tsx","componentPath":"./src/libs/ui/index.ts","tags":["dev","test","autodocs"]},"ui-animations--grow":{"type":"story","id":"ui-animations--grow","name":"Grow","title":"UI/Animations","importPath":"./src/stories/ui/animations.stories.tsx","componentPath":"./src/libs/ui/index.ts","tags":["dev","test","autodocs"]},"ui-animations--slide":{"type":"story","id":"ui-animations--slide","name":"Slide","title":"UI/Animations","importPath":"./src/stories/ui/animations.stories.tsx","componentPath":"./src/libs/ui/index.ts","tags":["dev","test","autodocs"]},"ui-animations--zoom":{"type":"story","id":"ui-animations--zoom","name":"Zoom","title":"UI/Animations","importPath":"./src/stories/ui/animations.stories.tsx","componentPath":"./src/libs/ui/index.ts","tags":["dev","test","autodocs"]},"ui-avatar-group--docs":{"id":"ui-avatar-group--docs","title":"UI/Avatar Group","name":"Docs","importPath":"./src/stories/ui/avatar-group.stories.tsx","type":"docs","tags":["dev","test","autodocs"],"storiesImports":[]},"ui-avatar-group--avatar-group":{"type":"story","id":"ui-avatar-group--avatar-group","name":"Avatar Group","title":"UI/Avatar Group","importPath":"./src/stories/ui/avatar-group.stories.tsx","componentPath":"./src/libs/ui/index.ts","tags":["dev","test","autodocs"]},"ui-avatar--docs":{"id":"ui-avatar--docs","title":"UI/Avatar","name":"Docs","importPath":"./src/stories/ui/avatar.stories.tsx","type":"docs","tags":["dev","test","autodocs"],"storiesImports":[]},"ui-avatar--image-avatar":{"type":"story","id":"ui-avatar--image-avatar","name":"Image Avatar","title":"UI/Avatar","importPath":"./src/stories/ui/avatar.stories.tsx","componentPath":"./src/libs/ui/index.ts","tags":["dev","test","autodocs"]},"ui-avatar--letter-avatar":{"type":"story","id":"ui-avatar--letter-avatar","name":"Letter Avatar","title":"UI/Avatar","importPath":"./src/stories/ui/avatar.stories.tsx","componentPath":"./src/libs/ui/index.ts","tags":["dev","test","autodocs"]},"ui-backdrop--docs":{"id":"ui-backdrop--docs","title":"UI/Backdrop","name":"Docs","importPath":"./src/stories/ui/backdrop.stories.tsx","type":"docs","tags":["dev","test","autodocs"],"storiesImports":[]},"ui-backdrop--backdrop":{"type":"story","id":"ui-backdrop--backdrop","name":"Backdrop","title":"UI/Backdrop","importPath":"./src/stories/ui/backdrop.stories.tsx","componentPath":"./src/libs/ui/index.ts","tags":["dev","test","autodocs"]},"ui-box--docs":{"id":"ui-box--docs","title":"UI/Box","name":"Docs","importPath":"./src/stories/ui/box.stories.tsx","type":"docs","tags":["dev","test","autodocs"],"storiesImports":[]},"ui-box--box":{"type":"story","id":"ui-box--box","name":"Box","title":"UI/Box","importPath":"./src/stories/ui/box.stories.tsx","componentPath":"./src/libs/ui/index.ts","tags":["dev","test","autodocs"]},"ui-box--flex-box":{"type":"story","id":"ui-box--flex-box","name":"Flex Box","title":"UI/Box","importPath":"./src/stories/ui/box.stories.tsx","componentPath":"./src/libs/ui/index.ts","tags":["dev","test","autodocs"]},"ui-box--inline-box":{"type":"story","id":"ui-box--inline-box","name":"Inline Box","title":"UI/Box","importPath":"./src/stories/ui/box.stories.tsx","componentPath":"./src/libs/ui/index.ts","tags":["dev","test","autodocs"]},"ui-button--docs":{"id":"ui-button--docs","title":"UI/Button","name":"Docs","importPath":"./src/stories/ui/button.stories.ts","type":"docs","tags":["dev","test","autodocs"],"storiesImports":[]},"ui-button--primary":{"type":"story","id":"ui-button--primary","name":"Primary","title":"UI/Button","importPath":"./src/stories/ui/button.stories.ts","componentPath":"./src/libs/ui/index.ts","tags":["dev","test","autodocs"]},"ui-button--primary-outline":{"type":"story","id":"ui-button--primary-outline","name":"Primary Outline","title":"UI/Button","importPath":"./src/stories/ui/button.stories.ts","componentPath":"./src/libs/ui/index.ts","tags":["dev","test","autodocs"]},"ui-button--secondary":{"type":"story","id":"ui-button--secondary","name":"Secondary","title":"UI/Button","importPath":"./src/stories/ui/button.stories.ts","componentPath":"./src/libs/ui/index.ts","tags":["dev","test","autodocs"]},"ui-button--secondary-outline":{"type":"story","id":"ui-button--secondary-outline","name":"Secondary Outline","title":"UI/Button","importPath":"./src/stories/ui/button.stories.ts","componentPath":"./src/libs/ui/index.ts","tags":["dev","test","autodocs"]},"ui-card--docs":{"id":"ui-card--docs","title":"UI/Card","name":"Docs","importPath":"./src/stories/ui/card.stories.tsx","type":"docs","tags":["dev","test","autodocs"],"storiesImports":[]},"ui-card--card":{"type":"story","id":"ui-card--card","name":"Card","title":"UI/Card","importPath":"./src/stories/ui/card.stories.tsx","componentPath":"./src/libs/ui/index.ts","tags":["dev","test","autodocs"]},"ui-checkbox--docs":{"id":"ui-checkbox--docs","title":"UI/Checkbox","name":"Docs","importPath":"./src/stories/ui/checkbox.stories.tsx","type":"docs","tags":["dev","test","autodocs"],"storiesImports":[]},"ui-checkbox--checkbox":{"type":"story","id":"ui-checkbox--checkbox","name":"Checkbox","title":"UI/Checkbox","importPath":"./src/stories/ui/checkbox.stories.tsx","componentPath":"./src/libs/ui/index.ts","tags":["dev","test","autodocs"]},"ui-chip--docs":{"id":"ui-chip--docs","title":"UI/Chip","name":"Docs","importPath":"./src/stories/ui/chip.stories.tsx","type":"docs","tags":["dev","test","autodocs"],"storiesImports":[]},"ui-chip--chip":{"type":"story","id":"ui-chip--chip","name":"Chip","title":"UI/Chip","importPath":"./src/stories/ui/chip.stories.tsx","componentPath":"./src/libs/ui/index.ts","tags":["dev","test","autodocs"]},"ui-container--docs":{"id":"ui-container--docs","title":"UI/Container","name":"Docs","importPath":"./src/stories/ui/container.stories.tsx","type":"docs","tags":["dev","test","autodocs"],"storiesImports":[]},"ui-container--container":{"type":"story","id":"ui-container--container","name":"Container","title":"UI/Container","importPath":"./src/stories/ui/container.stories.tsx","componentPath":"./src/libs/ui/index.ts","tags":["dev","test","autodocs"]},"ui-divider--docs":{"id":"ui-divider--docs","title":"UI/Divider","name":"Docs","importPath":"./src/stories/ui/divider.stories.tsx","type":"docs","tags":["dev","test","autodocs"],"storiesImports":[]},"ui-divider--divider":{"type":"story","id":"ui-divider--divider","name":"Divider","title":"UI/Divider","importPath":"./src/stories/ui/divider.stories.tsx","componentPath":"./src/libs/ui/index.ts","tags":["dev","test","autodocs"]},"ui-drawer--docs":{"id":"ui-drawer--docs","title":"UI/Drawer","name":"Docs","importPath":"./src/stories/ui/drawer.stories.tsx","type":"docs","tags":["dev","test","autodocs"],"storiesImports":[]},"ui-drawer--drawer":{"type":"story","id":"ui-drawer--drawer","name":"Drawer","title":"UI/Drawer","importPath":"./src/stories/ui/drawer.stories.tsx","componentPath":"./src/libs/ui/index.ts","tags":["dev","test","autodocs"]},"ui-grid--docs":{"id":"ui-grid--docs","title":"UI/Grid","name":"Docs","importPath":"./src/stories/ui/grid.stories.tsx","type":"docs","tags":["dev","test","autodocs"],"storiesImports":[]},"ui-grid--grid":{"type":"story","id":"ui-grid--grid","name":"Grid","title":"UI/Grid","importPath":"./src/stories/ui/grid.stories.tsx","componentPath":"./src/libs/ui/index.ts","tags":["dev","test","autodocs"]}}}